math_parser/Compute.py
math_parser/Node.py
math_parser/Parser.py
math_parser/__init__.py
Math_Parser-0.1.2.dist-info/METADATA
Math_Parser-0.1.2.dist-info/WHEEL
Math_Parser-0.1.2.dist-info/top_level.txt
Math_Parser-0.1.2.dist-info/RECORD
