Metadata-Version: 2.1
Name: Math-Parser
Version: 0.1.2
Summary: This package evaluates mathematics expressions written in string safely.
Home-page: https://github.com/victor-soeiro/Math-Parser
Author: Victor Soeiro
Author-email: victor.soeiro.araujo@gmail.com
License: MIT
Keywords: mathematics,expressions,compilers,evaluation
Classifier: Programming Language :: Python :: 3
Classifier: Intended Audience :: Science/Research
Classifier: Topic :: Scientific/Engineering :: Mathematics
Classifier: License :: OSI Approved :: MIT License
Requires-Python: >=3.6
